agent_steam/__init__.py
agent_steam/__main__.py
agent_steam/cli.py
agent_steam/core.py
agent_steam/adapters/__init__.py
agent_steam/adapters/base.py
agent_steam/adapters/claude.py
agent_steam/adapters/deepseek.py
agent_steam/adapters/registry.py
agent_steam/docker/__init__.py
agent_steam/docker/packager.py
agent_steam/io/__init__.py
agent_steam/io/manager.py
agent_steam/mcp/__init__.py
agent_steam/mcp/client.py
agent_steam/tools/__init__.py
agent_steam/tools/base.py
agent_steam/tools/registry.py
agent_steam/tools/predefined/__init__.py
agent_steam/tools/predefined/ask_for_clarification.py
agent_steam/tools/predefined/bash.py
agent_steam/tools/predefined/duckduckgo_search.py
agent_steam/tools/predefined/edit.py
agent_steam/tools/predefined/example_custom_schema.py
agent_steam/tools/predefined/file_tree.py
agent_steam/tools/predefined/glob.py
agent_steam/tools/predefined/grep.py
agent_steam/tools/predefined/ls.py
agent_steam/tools/predefined/read.py
agent_steam/tools/predefined/summary.py
agent_steam/tools/predefined/web_fetch.py
agent_steam/tools/predefined/write.py
agent_steam/utils/__init__.py
agent_steam/utils/logging.py
agent_steam-0.1.2.dist-info/METADATA
agent_steam-0.1.2.dist-info/WHEEL
agent_steam-0.1.2.dist-info/entry_points.txt
agent_steam-0.1.2.dist-info/top_level.txt
agent_steam-0.1.2.dist-info/RECORD
